behave/__init__.py
behave/__main__.py
behave/_stepimport.py
behave/_types.py
behave/async_step.py
behave/capture.py
behave/configuration.py
behave/constant.py
behave/cucumber_expression.py
behave/exception.py
behave/exception_util.py
behave/fixture.py
behave/i18n.py
behave/importer.py
behave/json_parser.py
behave/log_capture.py
behave/log_config.py
behave/matchers.py
behave/model.py
behave/model_core.py
behave/model_describe.py
behave/model_type.py
behave/model_visitor.py
behave/parameter_type.py
behave/parser.py
behave/pathutil.py
behave/python_feature.py
behave/runner.py
behave/runner_plugin.py
behave/runner_util.py
behave/step_registry.py
behave/summary.py
behave/tag_matcher.py
behave/textutil.py
behave/userdata.py
behave/version.py
behave/active_tag/__init__.py
behave/active_tag/python.py
behave/active_tag/python_feature.py
behave/api/__init__.py
behave/api/async_step.py
behave/api/formatter.py
behave/api/pending_step.py
behave/api/runner.py
behave/api/runtime_constraint.py
behave/api/step_matchers.py
behave/compat/__init__.py
behave/compat/collections.py
behave/compat/exceptions.py
behave/contrib/__init__.py
behave/contrib/csv_table_from_file.py
behave/contrib/formatter_missing_steps.py
behave/contrib/scenario_autoretry.py
behave/contrib/substep_dirs.py
behave/formatter/__init__.py
behave/formatter/_builtins.py
behave/formatter/_registry.py
behave/formatter/ansi_escapes.py
behave/formatter/api.py
behave/formatter/bad_steps.py
behave/formatter/base.py
behave/formatter/base2.py
behave/formatter/captured.py
behave/formatter/formatters.py
behave/formatter/json.py
behave/formatter/null.py
behave/formatter/plain.py
behave/formatter/pretty.py
behave/formatter/progress.py
behave/formatter/rerun.py
behave/formatter/sphinx_steps.py
behave/formatter/sphinx_util.py
behave/formatter/steps.py
behave/formatter/steps_code.py
behave/formatter/tags.py
behave/reporter/__init__.py
behave/reporter/base.py
behave/reporter/junit.py
behave/reporter/summary.py
behave-1.3.2.dist-info/licenses/LICENSE
behave-1.3.2.dist-info/METADATA
behave-1.3.2.dist-info/WHEEL
behave-1.3.2.dist-info/entry_points.txt
behave-1.3.2.dist-info/top_level.txt
behave-1.3.2.dist-info/zip-safe
behave-1.3.2.dist-info/RECORD
