Metadata-Version: 2.4
Name: behave
Version: 1.3.2
Summary: behave is behaviour-driven development, Python style
Author: Benno Rice, Richard Jones
Author-email: Jens Engel <jenisys@noreply.github.com>
Maintainer: Jens Engel, Peter Bittner
Maintainer-email: Jens Engel <jenisys@noreply.github.com>, Peter Bittner <bittner@noreply.github.com>
License-Expression: BSD-2-Clause
Project-URL: Homepage, https://github.com/behave/behave
Project-URL: Documentation, https://behave.readthedocs.io/en/latest/
Project-URL: Repository, https://github.com/behave/behave
Project-URL: Issues, https://github.com/behave/behave/issues/
Project-URL: Changelog, https://github.com/behave/behave/blob/main/CHANGES.rst
Keywords: BDD,behavior-driven-development,bdd-framework,behave,gherkin,cucumber-like
Platform: any
Classifier: Development Status :: 5 - Production/Stable
Classifier: Environment :: Console
Classifier: Intended Audience :: Developers
Classifier: Operating System :: OS Independent
Classifier: Programming Language :: Python :: 2
Classifier: Programming Language :: Python :: 2.7
Classifier: Programming Language :: Python :: 3
Classifier: Programming Language :: Python :: 3.5
Classifier: Programming Language :: Python :: 3.6
Classifier: Programming Language :: Python :: 3.7
Classifier: Programming Language :: Python :: 3.8
Classifier: Programming Language :: Python :: 3.9
Classifier: Programming Language :: Python :: 3.10
Classifier: Programming Language :: Python :: 3.11
Classifier: Programming Language :: Python :: 3.12
Classifier: Programming Language :: Python :: 3.13
Classifier: Programming Language :: Python :: Implementation :: CPython
Classifier: Programming Language :: Python :: Implementation :: Jython
Classifier: Programming Language :: Python :: Implementation :: PyPy
Classifier: Topic :: Software Development :: Testing
Provides: behave
Requires-Python: !=3.0.*,!=3.1.*,!=3.2.*,>=2.7
License-File: LICENSE
Requires-Dist: cucumber-tag-expressions>=4.1.0
Requires-Dist: cucumber-expressions>=17.1.0; python_version >= "3.8"
Requires-Dist: enum34; python_version < "3.4"
Requires-Dist: parse>=1.18.0
Requires-Dist: parse-type>=0.6.0
Requires-Dist: six>=1.15.0
Requires-Dist: traceback2; python_version < "3.0"
Requires-Dist: scandir>=1.10.0; python_version < "3.5"
Requires-Dist: win_unicode_console; python_version <= "3.9"
Requires-Dist: contextlib2; python_version < "3.5"
Requires-Dist: colorama>=0.3.7
Requires-Dist: tomli>=1.1.0; python_version >= "3.0" and python_version < "3.11"
Requires-Dist: toml>=0.10.2; python_version < "3.0"
Provides-Extra: develop
Requires-Dist: build>=0.5.1; extra == "develop"
Requires-Dist: twine>=1.13.0; extra == "develop"
Requires-Dist: coverage>=5.0; extra == "develop"
Requires-Dist: pytest<5.0,>=4.2; python_version < "3.0" and extra == "develop"
Requires-Dist: pytest>=5.0; python_version >= "3.0" and extra == "develop"
Requires-Dist: pytest-html<2.0,>=1.19.0; python_version < "3.0" and extra == "develop"
Requires-Dist: pytest-html>=2.0; python_version >= "3.0" and extra == "develop"
Requires-Dist: mock<4.0; python_version < "3.6" and extra == "develop"
Requires-Dist: mock>=4.0; python_version >= "3.6" and extra == "develop"
Requires-Dist: PyHamcrest>=2.0.2; python_version >= "3.0" and extra == "develop"
Requires-Dist: PyHamcrest<2.0; python_version < "3.0" and extra == "develop"
Requires-Dist: pytest-cov; extra == "develop"
Requires-Dist: tox<4.0,>=3.28.0; extra == "develop"
Requires-Dist: virtualenv>=20.26.6; python_version >= "3.7" and extra == "develop"
Requires-Dist: virtualenv<20.22.0; python_version < "3.7" and extra == "develop"
Requires-Dist: invoke<2.0,>=1.7.0; python_version < "3.6" and extra == "develop"
Requires-Dist: invoke>=1.7.0; python_version >= "3.6" and extra == "develop"
Requires-Dist: path>=13.1.0; python_version >= "3.5" and extra == "develop"
Requires-Dist: path.py>=11.5.0; python_version < "3.5" and extra == "develop"
Requires-Dist: pycmd; extra == "develop"
Requires-Dist: pathlib; python_version <= "3.4" and extra == "develop"
Requires-Dist: modernize>=0.5; extra == "develop"
Requires-Dist: pylint; extra == "develop"
Requires-Dist: ruff; python_version >= "3.7" and extra == "develop"
Provides-Extra: docs
Requires-Dist: sphinx>=7.4.0; python_version >= "3.7" and extra == "docs"
Requires-Dist: sphinx<4.4,>=1.6; python_version < "3.7" and extra == "docs"
Requires-Dist: furo>=2024.04.27; python_version >= "3.8" and extra == "docs"
Requires-Dist: sphinxcontrib-applehelp>=1.0.8; python_version >= "3.7" and extra == "docs"
Requires-Dist: sphinxcontrib-htmlhelp>=2.0.5; python_version >= "3.7" and extra == "docs"
Requires-Dist: sphinx-copybutton>=0.5.2; python_version >= "3.7" and extra == "docs"
Provides-Extra: formatters
Requires-Dist: behave-html-formatter>=0.9.10; python_version >= "3.6" and extra == "formatters"
Requires-Dist: behave-html-pretty-formatter>=1.9.1; python_version >= "3.6" and extra == "formatters"
Provides-Extra: testing
Requires-Dist: pytest<5.0; python_version < "3.0" and extra == "testing"
Requires-Dist: pytest>=5.0; python_version >= "3.0" and extra == "testing"
Requires-Dist: pytest-html<2.0,>=1.19.0; python_version < "3.0" and extra == "testing"
Requires-Dist: pytest-html>=2.0; python_version >= "3.0" and extra == "testing"
Requires-Dist: mock<4.0; python_version < "3.6" and extra == "testing"
Requires-Dist: mock>=4.0; python_version >= "3.6" and extra == "testing"
Requires-Dist: PyHamcrest>=2.0.2; python_version >= "3.0" and extra == "testing"
Requires-Dist: PyHamcrest<2.0; python_version < "3.0" and extra == "testing"
Requires-Dist: assertpy>=1.1; extra == "testing"
Requires-Dist: chardet; extra == "testing"
Requires-Dist: path>=13.1.0; python_version >= "3.5" and extra == "testing"
Requires-Dist: path.py<13.0,>=11.5.0; python_version < "3.5" and extra == "testing"
Requires-Dist: pathlib; python_version <= "3.4" and extra == "testing"
Requires-Dist: freezegun>=1.5.1; python_version > "3.7" and extra == "testing"
Dynamic: license-file
Dynamic: provides
